{
	"configurations" : 
	[
		{
			"directories" : 
			[
				{
					"build" : ".",
					"childIndexes" : 
					[
						1
					],
					"jsonFile" : "directory-.-Debug-f5ebdc15457944623624.json",
					"minimumCMakeVersion" : 
					{
						"string" : "3.16"
					},
					"projectIndex" : 0,
					"source" : "."
				},
				{
					"build" : "src",
					"childIndexes" : 
					[
						2,
						3,
						4,
						5
					],
					"jsonFile" : "directory-src-Debug-b6cf2213fc5053b67c22.json",
					"minimumCMakeVersion" : 
					{
						"string" : "3.16"
					},
					"parentIndex" : 0,
					"projectIndex" : 0,
					"source" : "src",
					"targetIndexes" : 
					[
						3
					]
				},
				{
					"build" : "src/Communications",
					"jsonFile" : "directory-src.Communications-Debug-7290cba179cb29fec316.json",
					"minimumCMakeVersion" : 
					{
						"string" : "3.16"
					},
					"parentIndex" : 1,
					"projectIndex" : 0,
					"source" : "src/Communications",
					"targetIndexes" : 
					[
						0
					]
				},
				{
					"build" : "src/Logger",
					"jsonFile" : "directory-src.Logger-Debug-18262c2bdca6287e1b99.json",
					"minimumCMakeVersion" : 
					{
						"string" : "3.16"
					},
					"parentIndex" : 1,
					"projectIndex" : 0,
					"source" : "src/Logger",
					"targetIndexes" : 
					[
						1
					]
				},
				{
					"build" : "src/Manager",
					"jsonFile" : "directory-src.Manager-Debug-fbaffd8c9592b2a51b65.json",
					"minimumCMakeVersion" : 
					{
						"string" : "3.16"
					},
					"parentIndex" : 1,
					"projectIndex" : 0,
					"source" : "src/Manager"
				},
				{
					"build" : "src/Protocols",
					"jsonFile" : "directory-src.Protocols-Debug-0ef3943ce78c08e8ba82.json",
					"minimumCMakeVersion" : 
					{
						"string" : "3.16"
					},
					"parentIndex" : 1,
					"projectIndex" : 0,
					"source" : "src/Protocols",
					"targetIndexes" : 
					[
						2
					]
				}
			],
			"name" : "Debug",
			"projects" : 
			[
				{
					"directoryIndexes" : 
					[
						0,
						1,
						2,
						3,
						4,
						5
					],
					"name" : "Stock_Simulator",
					"targetIndexes" : 
					[
						0,
						1,
						2,
						3
					]
				}
			],
			"targets" : 
			[
				{
					"directoryIndex" : 2,
					"id" : "COMMUNICATIONS_LIB::@35a6a6d2c96d13e300b4",
					"jsonFile" : "target-COMMUNICATIONS_LIB-Debug-626e9e330ce24e1a441a.json",
					"name" : "COMMUNICATIONS_LIB",
					"projectIndex" : 0
				},
				{
					"directoryIndex" : 3,
					"id" : "LOGGER_LIB::@8f2c0937412c0976db5b",
					"jsonFile" : "target-LOGGER_LIB-Debug-12222409d22ff6e6b823.json",
					"name" : "LOGGER_LIB",
					"projectIndex" : 0
				},
				{
					"directoryIndex" : 5,
					"id" : "PROTOCOL_LIB::@0d6d85245ab30f279b0c",
					"jsonFile" : "target-PROTOCOL_LIB-Debug-fbf56eff003fa8786136.json",
					"name" : "PROTOCOL_LIB",
					"projectIndex" : 0
				},
				{
					"directoryIndex" : 1,
					"id" : "Simulator::@145eef247bfb46b6828c",
					"jsonFile" : "target-Simulator-Debug-e7263207ee4e95d2b0fe.json",
					"name" : "Simulator",
					"projectIndex" : 0
				}
			]
		}
	],
	"kind" : "codemodel",
	"paths" : 
	{
		"build" : "/app/build",
		"source" : "/app"
	},
	"version" : 
	{
		"major" : 2,
		"minor" : 6
	}
}
